pyomega/__init__.py
pyomega/aws_client.py
pyomega/database.py
pyomega/helper.py
pyomega-0.1.17.dist-info/LICENSE
pyomega-0.1.17.dist-info/METADATA
pyomega-0.1.17.dist-info/WHEEL
pyomega-0.1.17.dist-info/top_level.txt
pyomega-0.1.17.dist-info/RECORD
