Metadata-Version: 2.1
Name: pyomega
Version: 0.1.17
Summary: A small example package
Home-page: https://github.com/
Author: Omega
Author-email: example@example.com
License: UNKNOWN
Platform: UNKNOWN
Classifier: Programming Language :: Python :: 3
Classifier: License :: OSI Approved :: MIT License
Classifier: Operating System :: OS Independent
Requires-Python: >=3.6
License-File: LICENSE
